<annotation>
	<folder>720kb</folder>
	<filename>IMG_20180616_195936.jpg</filename>
	<path>C:\Users\jhanw\Desktop\720kb\IMG_20180616_195936.jpg</path>
	<source>
		<database>Unknown</database>
	</source>
	<size>
		<width>899</width>
		<height>899</height>
		<depth>3</depth>
	</size>
	<segmented>0</segmented>
	<object>
		<name>Honey Comb- 009288857</name>
		<pose>Unspecified</pose>
		<truncated>1</truncated>
		<difficult>0</difficult>
		<bndbox>
			<xmin>1</xmin>
			<ymin>685</ymin>
			<xmax>281</xmax>
			<ymax>885</ymax>
		</bndbox>
	</object>
	<object>
		<name>Oreo-563424384</name>
		<pose>Unspecified</pose>
		<truncated>0</truncated>
		<difficult>0</difficult>
		<bndbox>
			<xmin>352</xmin>
			<ymin>649</ymin>
			<xmax>598</xmax>
			<ymax>799</ymax>
		</bndbox>
	</object>
	<object>
		<name>Chips Ahoys-565717529</name>
		<pose>Unspecified</pose>
		<truncated>1</truncated>
		<difficult>0</difficult>
		<bndbox>
			<xmin>651</xmin>
			<ymin>466</ymin>
			<xmax>899</xmax>
			<ymax>626</ymax>
		</bndbox>
	</object>
</annotation>
